unitycatalog/ai/core/__init__.py
unitycatalog/ai/core/base.py
unitycatalog/ai/core/client.py
unitycatalog/ai/core/databricks.py
unitycatalog/ai/core/paged_list.py
unitycatalog/ai/core/types.py
unitycatalog/ai/core/version.py
unitycatalog/ai/core/envs/base.py
unitycatalog/ai/core/envs/databricks_env_vars.py
unitycatalog/ai/core/envs/executor_env_vars.py
unitycatalog/ai/core/executor/common.py
unitycatalog/ai/core/executor/local.py
unitycatalog/ai/core/executor/local_subprocess.py
unitycatalog/ai/core/utils/__init__.py
unitycatalog/ai/core/utils/callable_utils.py
unitycatalog/ai/core/utils/callable_utils_oss.py
unitycatalog/ai/core/utils/client_utils.py
unitycatalog/ai/core/utils/config.py
unitycatalog/ai/core/utils/docstring_utils.py
unitycatalog/ai/core/utils/execution_utils.py
unitycatalog/ai/core/utils/function_processing_utils.py
unitycatalog/ai/core/utils/pydantic_utils.py
unitycatalog/ai/core/utils/retry_utils.py
unitycatalog/ai/core/utils/type_utils.py
unitycatalog/ai/core/utils/validation_utils.py
unitycatalog_ai-0.3.1.dist-info/METADATA
unitycatalog_ai-0.3.1.dist-info/WHEEL
unitycatalog_ai-0.3.1.dist-info/RECORD
