Metadata-Version: 2.4
Name: unitycatalog-ai
Version: 0.3.1
Summary: Official Python library for Unity Catalog AI support
Project-URL: homepage, https://www.unitycatalog.io/
Project-URL: issues, https://github.com/unitycatalog/unitycatalog/issues
Project-URL: repository, https://github.com/unitycatalog/unitycatalog
Author-email: Serena Ruan <serena.ruan@databricks.com>, Ben Wilson <benjamin.wilson@databricks.com>
Maintainer-email: Serena Ruan <serena.ruan@databricks.com>, Ben Wilson <benjamin.wilson@databricks.com>
License: Apache-2.0
Keywords: ai,databricks,function,genai,tool,unitycatalog
Classifier: Development Status :: 4 - Beta
Classifier: Intended Audience :: Developers
Classifier: Intended Audience :: Education
Classifier: Intended Audience :: End Users/Desktop
Classifier: Intended Audience :: Information Technology
Classifier: Intended Audience :: Other Audience
Classifier: Intended Audience :: Science/Research
Classifier: License :: OSI Approved :: Apache Software License
Classifier: Operating System :: OS Independent
Classifier: Programming Language :: Python :: 3
Classifier: Programming Language :: Python :: 3.9
Classifier: Programming Language :: Python :: 3.10
Classifier: Programming Language :: Python :: 3.11
Classifier: Programming Language :: Python :: 3.12
Classifier: Topic :: Scientific/Engineering
Classifier: Topic :: Scientific/Engineering :: Artificial Intelligence
Classifier: Topic :: Software Development
Classifier: Topic :: Software Development :: Libraries
Classifier: Topic :: Software Development :: Libraries :: Python Modules
Classifier: Topic :: Software Development :: User Interfaces
Requires-Python: >=3.9
Requires-Dist: cloudpickle
Requires-Dist: nest-asyncio
Requires-Dist: pydantic
Requires-Dist: typing-extensions
Requires-Dist: unitycatalog-client
Provides-Extra: databricks
Requires-Dist: databricks-connect<16.4,>=15.1.0; extra == 'databricks'
Requires-Dist: databricks-sdk>=0.32.0; extra == 'databricks'
Requires-Dist: pandas; extra == 'databricks'
Provides-Extra: databricks-dev
Requires-Dist: databricks-connect<16.4,>=15.1.0; extra == 'databricks-dev'
Requires-Dist: databricks-sdk>=0.32.0; extra == 'databricks-dev'
Requires-Dist: hatch; extra == 'databricks-dev'
Requires-Dist: pandas; extra == 'databricks-dev'
Requires-Dist: pytest; extra == 'databricks-dev'
Requires-Dist: ruff==0.9.3; extra == 'databricks-dev'
Provides-Extra: dev
Requires-Dist: databricks-connect<16.4; extra == 'dev'
Requires-Dist: databricks-sdk>=0.32.0; extra == 'dev'
Requires-Dist: hatch; extra == 'dev'
Requires-Dist: pandas; extra == 'dev'
Requires-Dist: pytest; extra == 'dev'
Requires-Dist: pytest-asyncio; extra == 'dev'
Requires-Dist: ruff==0.9.3; extra == 'dev'
